Metadata-Version: 2.1
Name: xycepymi
Version: 7.4.0
Summary: Xyce
Home-page: https://github.com/Xyce/Xyce
Author: Xyce Team
Author-email: xyce@sandia.gov
License: UNKNOWN
Project-URL: Bug Tracker, https://github.com/Xyce/Xyce/issues
Platform: UNKNOWN
Classifier: Programming Language :: Python :: 3
Classifier: License :: OSI Approved :: GNU General Public License v3 (GPLv3)
Classifier: Operating System :: OS Independent
Requires-Python: >=3.6
